README.rst
setup.py
pymysqlblinker/__init__.py
pymysqlblinker/binlog_pos_memory.py
pymysqlblinker/pub.py
pymysqlblinker/signals.py
pymysqlblinker.egg-info/PKG-INFO
pymysqlblinker.egg-info/SOURCES.txt
pymysqlblinker.egg-info/dependency_links.txt
pymysqlblinker.egg-info/not-zip-safe
pymysqlblinker.egg-info/pbr.json
pymysqlblinker.egg-info/requires.txt
pymysqlblinker.egg-info/top_level.txt