Metadata-Version: 1.1
Name: pymysqlblinker
Version: 1.2
Summary: mysql binlog to blinker signal
Home-page: https://github.com/tarzanjw/python-mysql-replication-blinker
Author: Hoc .T Do
Author-email: hoc3010@gmail.com
License: MIT
Keywords: event replication mysql signal
Platform: UNKNOWN
Classifier: Topic :: Software Development
Classifier: Development Status :: 3 - Alpha
Classifier: Intended Audience :: Developers
Classifier: License :: OSI Approved :: MIT License
Classifier: Programming Language :: Python :: 2.7
Classifier: Programming Language :: Python :: 3.4
